multi_exchange_price_aggregator/__init__.py
multi_exchange_price_aggregator/aggregator.py
tests/__init__.py
tests/test_aggregator.py
multi_exchange_price_aggregator-0.1.1.dist-info/METADATA
multi_exchange_price_aggregator-0.1.1.dist-info/WHEEL
multi_exchange_price_aggregator-0.1.1.dist-info/top_level.txt
multi_exchange_price_aggregator-0.1.1.dist-info/RECORD
