Metadata-Version: 2.1
Name: multi_exchange_price_aggregator
Version: 0.1.1
Summary: A package for aggregating cryptocurrency prices from multiple exchanges.
Home-page: https://github.com/hedeqiang/multi_exchange_price_aggregator
Author: hedeqiang
Author-email: laravel_code@163.com
Classifier: Programming Language :: Python :: 3
Classifier: License :: OSI Approved :: MIT License
Classifier: Operating System :: OS Independent
Requires-Python: >=3.6
Requires-Dist: requests
